libxd/__init__.py
libxd/io.py
libxd-0.0.1.dist-info/DESCRIPTION.rst
libxd-0.0.1.dist-info/METADATA
libxd-0.0.1.dist-info/RECORD
libxd-0.0.1.dist-info/WHEEL
libxd-0.0.1.dist-info/entry_points.txt
libxd-0.0.1.dist-info/metadata.json
libxd-0.0.1.dist-info/top_level.txt
tests/__init__.py
tests/io/__init__.py
tests/io/test_file_utils.py
